cresset/__init__.py
cresset/py.typed
cresset/nn/__init__.py
cresset/nn/init.py
cresset/nn/module.py
cresset/nn/std.py
cresset/optim/__init__.py
cresset/optim/lr_scheduler.py
cresset-0.1.1.dist-info/METADATA
cresset-0.1.1.dist-info/WHEEL
cresset-0.1.1.dist-info/licenses/LICENSE
cresset-0.1.1.dist-info/RECORD
