Metadata-Version: 2.1
Name: cresset
Version: 0.1.1
Summary: Instantiate Python objects with Jsonnet
Project-URL: Source, https://git.sr.ht/~dojoteef/cresset
Project-URL: Mailing List, https://lists.sr.ht/~dojoteef/cresset
Author-email: Nader Akoury <~dojoteef/cresset-devel@lists.sr.ht>
License-Expression: MIT
License-File: LICENSE
Classifier: Development Status :: 3 - Alpha
Classifier: Intended Audience :: Developers
Classifier: License :: OSI Approved :: MIT License
Classifier: Operating System :: OS Independent
Classifier: Programming Language :: Python :: 3
Classifier: Programming Language :: Python :: 3 :: Only
Classifier: Programming Language :: Python :: 3.6
Classifier: Programming Language :: Python :: 3.7
Classifier: Programming Language :: Python :: 3.8
Classifier: Programming Language :: Python :: 3.9
Classifier: Programming Language :: Python :: 3.10
Classifier: Programming Language :: Python :: 3.11
Classifier: Programming Language :: Python :: 3.12
Classifier: Typing :: Typed
Requires-Python: >=3.6
Requires-Dist: confactory==0.1
Requires-Dist: torch>=1.4
Provides-Extra: codeqa
Requires-Dist: ruff; extra == 'codeqa'
Provides-Extra: dev
Requires-Dist: cresset[codeqa]; extra == 'dev'
Requires-Dist: cresset[formatters]; extra == 'dev'
Requires-Dist: cresset[typing]; extra == 'dev'
Provides-Extra: formatters
Requires-Dist: black; extra == 'formatters'
Requires-Dist: isort; extra == 'formatters'
Provides-Extra: typing
Requires-Dist: mypy; extra == 'typing'
